mapel/core/__init__.py
mapel/core/features_main.py
mapel/core/glossary.py
mapel/core/inner_distances.py
mapel/core/matchings.py
mapel/core/printing.py
mapel/core/utils.py
mapel/core/embedding/__init__.py
mapel/core/embedding/embed.py
mapel/core/embedding/initial_positions.py
mapel/core/embedding/kamada_kawai/__init__.py
mapel/core/embedding/kamada_kawai/energy_functions.py
mapel/core/embedding/kamada_kawai/kamada_kawai.py
mapel/core/embedding/kamada_kawai/optimization_algorithms.py
mapel/core/embedding/simulated_annealing/__init__.py
mapel/core/embedding/simulated_annealing/simulated_annealing.py
mapel/core/embedding/simulated_annealing/simulated_annealing_energy.py
mapel/core/features/__init__.py
mapel/core/features/common.py
mapel/core/features/distortion.py
mapel/core/features/mallows.py
mapel/core/features/monotonicity.py
mapel/core/features/stability.py
mapel/core/objects/Experiment.py
mapel/core/objects/Family.py
mapel/core/objects/Instance.py
mapel/core/objects/__init__.py
mapel/core/persistence/__init__.py
mapel/core/persistence/experiment_exports.py
mapel/core/persistence/experiment_imports.py
mapel_core-2.1.11.dist-info/LICENSE.txt
mapel_core-2.1.11.dist-info/METADATA
mapel_core-2.1.11.dist-info/WHEEL
mapel_core-2.1.11.dist-info/top_level.txt
mapel_core-2.1.11.dist-info/RECORD
