Metadata-Version: 2.1
Name: mapel-core
Version: 2.1.11
Summary: Map of Elections---essential parts
Author-email: Stanislaw Szufa <s.szufa@gmail.com>, Niclas Boehmer <niclas.boehmer@tu-berlin.de>, Andrzej Kaczmarczyk <andrzej.kaczmarczyk@agh.edu.pl>, Kasper Sapala <kasper.sapala@gmail.com>, Tomasz Was <tomasz.t.was@gmail.com>
License: Copyright (c) 2018-2022 Stanisław Szufa and contributors
Classifier: Programming Language :: Python :: 3
Classifier: License :: OSI Approved :: MIT License
Classifier: Operating System :: OS Independent
Requires-Python: >=3.7
License-File: LICENSE.txt
Requires-Dist: numpy ~=1.24.4
Requires-Dist: matplotlib ~=3.7.2
Requires-Dist: pillow ~=10.0.0
Requires-Dist: scipy ~=1.10.1
Requires-Dist: networkx ~=3.1
Requires-Dist: scikit-learn ~=1.3.0
Requires-Dist: tikzplotlib ~=0.10.1
Requires-Dist: tqdm ~=4.66.0
Requires-Dist: gurobipy ~=10.0.2
Requires-Dist: prefsampling ==0.1.15
